api_deezer/__init__.py
api_deezer/api.py
api_deezer/exceptions/__init__.py
api_deezer/exceptions/data.py
api_deezer/exceptions/links.py
api_deezer/py.typed
api_deezer/types/__init__.py
api_deezer/types/album.py
api_deezer/types/artist.py
api_deezer/types/chart.py
api_deezer/types/contributor.py
api_deezer/types/explicit_content.py
api_deezer/types/genre.py
api_deezer/types/playlist.py
api_deezer/types/search.py
api_deezer/types/track.py
api_deezer/utils.py
api_deezer-0.0.1b7.dist-info/METADATA
api_deezer-0.0.1b7.dist-info/WHEEL
api_deezer-0.0.1b7.dist-info/RECORD
