Metadata-Version: 2.1
Name: api-deezer
Version: 0.0.1b7
Summary: Wrapper for public deezer APIs
License: CC BY 4.0
Author: An0nimia
Author-email: an0nimia@protonmail.com
Requires-Python: >=3.12,<4.0
Classifier: License :: Other/Proprietary License
Classifier: Programming Language :: Python :: 3
Classifier: Programming Language :: Python :: 3.12
Classifier: Programming Language :: Python :: 3.13
Requires-Dist: pydantic (>=2.4.1,<3.0.0)
Requires-Dist: requests (>=2.31.0,<3.0.0)
